tap_brevo/__init__.py
tap_brevo/__main__.py
tap_brevo/client.py
tap_brevo/schemas/__init__.py
tap_brevo/streams.py
tap_brevo/tap.py
tap_brevo-0.0.5.dist-info/METADATA
tap_brevo-0.0.5.dist-info/WHEEL
tap_brevo-0.0.5.dist-info/entry_points.txt
tap_brevo-0.0.5.dist-info/RECORD
