Metadata-Version: 2.1
Name: tap-brevo
Version: 0.0.5
Summary: Singer tap for brevo, built with the Meltano Singer SDK.
License: Apache-2.0
Keywords: ELT,brevo
Author: Lesedi Kwatsherema
Author-email: lesedi@oviond.com
Requires-Python: >=3.9
Classifier: Intended Audience :: Developers
Classifier: License :: OSI Approved :: Apache Software License
Classifier: Operating System :: OS Independent
Classifier: Programming Language :: Python :: 3
Classifier: Programming Language :: Python :: 3.9
Classifier: Programming Language :: Python :: 3.10
Classifier: Programming Language :: Python :: 3.11
Classifier: Programming Language :: Python :: 3.12
Provides-Extra: s3
Requires-Dist: fs-s3fs (>=1.1.1,<1.2.0) ; extra == "s3"
Requires-Dist: requests (>=2.32.3,<2.33.0)
Requires-Dist: singer-sdk (>=0.41.0,<0.42.0)
